reference_handler/__init__.py
reference_handler/_version.py
reference_handler/latex_utf8.py
reference_handler/reference_handler.py
reference_handler/utils.py
reference_handler/tests/__init__.py
reference_handler/tests/build_filenames.py
reference_handler/tests/test_exceptions.py
reference_handler/tests/test_latex.py
reference_handler/tests/test_reference_handler.py
reference_handler/tests/data/library.bib
reference_handler/tests/scratch/database.db
reference_handler/tests/scratch/outfile.bib
reference_handler/tests/scratch/tmp.db
reference_handler-0.9.1.dist-info/LICENSE
reference_handler-0.9.1.dist-info/METADATA
reference_handler-0.9.1.dist-info/WHEEL
reference_handler-0.9.1.dist-info/top_level.txt
reference_handler-0.9.1.dist-info/RECORD
