Metadata-Version: 2.1
Name: reference-handler
Version: 0.9.1
Summary: UNKNOWN
Home-page: UNKNOWN
Author: MolSSI
Author-email: meliseo@vt.edu
License: BSD-3-Clause
Keywords: reference_handler
Platform: UNKNOWN
Classifier: Development Status :: 2 - Pre-Alpha
Classifier: Intended Audience :: Science/Research
Classifier: License :: OSI Approved :: BSD License
Classifier: Natural Language :: English
Classifier: Programming Language :: Python :: 3 :: Only
Classifier: Programming Language :: Python :: 3.6
Classifier: Programming Language :: Python :: 3.7
Requires-Dist: bibtexparser
